cfbd_json_py/__init__.py
cfbd_json_py/_early_access.py
cfbd_json_py/betting.py
cfbd_json_py/coaches.py
cfbd_json_py/conferences.py
cfbd_json_py/draft.py
cfbd_json_py/drives.py
cfbd_json_py/games.py
cfbd_json_py/metrics.py
cfbd_json_py/players.py
cfbd_json_py/plays.py
cfbd_json_py/rankings.py
cfbd_json_py/ratings.py
cfbd_json_py/recruiting.py
cfbd_json_py/stats.py
cfbd_json_py/teams.py
cfbd_json_py/utls.py
cfbd_json_py/venues.py
cfbd_json_py-0.2.4.dist-info/LICENSE
cfbd_json_py-0.2.4.dist-info/METADATA
cfbd_json_py-0.2.4.dist-info/WHEEL
cfbd_json_py-0.2.4.dist-info/top_level.txt
cfbd_json_py-0.2.4.dist-info/RECORD
