Metadata-Version: 2.1
Name: cfbd_json_py
Version: 0.2.4
Summary: Allows users to access the CFBD API, and get the resulting data in either a dictionary (think JSON), or in a pandas DataFrame (think spreadsheet).
Author-email: Joseph Armstrong <armstrongjoseph08@gmail.com>
Maintainer-email: Joseph Armstrong <armstrongjoseph08@gmail.com>
License: MIT
Project-URL: homepage, https://github.com/armstjc/cfbd-json-py
Project-URL: documentation, https://armstjc.github.io/cfbd-json-py/cfbd_json_py.html
Project-URL: repository, https://github.com/armstjc/cfbd-json-py.git
Project-URL: changelog, https://github.com/armstjc/cfbd-json-py/blob/main/CHANGELOG.md
Keywords: sports,football,college,college football
Classifier: Programming Language :: Python
Classifier: Programming Language :: Python :: 3
Classifier: Programming Language :: Python :: 3.10
Classifier: Programming Language :: Python :: 3.11
Classifier: Programming Language :: Python :: 3.12
Classifier: Programming Language :: Python :: 3.13
Requires-Python: >=3.10
License-File: LICENSE
Requires-Dist: setuptools>=67.6.0
Requires-Dist: wheel
Requires-Dist: pyarrow>=11.0.0
Requires-Dist: pandas>=2.2.2
Requires-Dist: tqdm
Requires-Dist: requests
Requires-Dist: keyring
